teller_cli/__init__.py
teller_cli/__main__.py
teller_cli/core/__init__.py
teller_cli/core/config.py
teller_cli/core/utils/__init__.py
teller_cli/core/world/__init__.py
teller_cli/core/world/download.py
teller_cli-0.3.10.dist-info/WHEEL
teller_cli-0.3.10.dist-info/entry_points.txt
teller_cli-0.3.10.dist-info/METADATA
teller_cli-0.3.10.dist-info/RECORD
