Metadata-Version: 2.1
Name: teller-cli
Version: 0.3.10
Summary: 
Author: JakePIXL
Author-email: jakewjevans@gmail.com
Requires-Python: >=3.9,<4.0
Classifier: Programming Language :: Python :: 3
Classifier: Programming Language :: Python :: 3.9
Classifier: Programming Language :: Python :: 3.10
Classifier: Programming Language :: Python :: 3.11
Requires-Dist: httpx (>=0.23.3,<0.24.0)
Requires-Dist: keyring (>=23.13.1,<24.0.0)
Requires-Dist: nanoid (>=2.0.0,<3.0.0)
Requires-Dist: nanoid-dictionary (>=2.4.0,<3.0.0)
Requires-Dist: nbtlib (>=2.0.4,<3.0.0)
Requires-Dist: prompt-toolkit (>=3.0.38,<4.0.0)
Requires-Dist: python-slugify (>=8.0.1,<9.0.0)
Requires-Dist: typer[all] (>=0.7.0,<0.8.0)
